<?xml version="1.0" encoding="utf-8" ?>
<dwsync>
<file name="class.core.php" server="ftp.mediaworks.hu//www/wwwtemp/chakra/" local="3443542576" remote="321191131148746312" Dst="-1" />
<file name="class.datetime.php" server="ftp.mediaworks.hu//www/wwwtemp/chakra/" local="3445013147" remote="323953104361273964" Dst="-1" />
<file name="class.language.php" server="ftp.mediaworks.hu//www/wwwtemp/chakra/" local="3443542583" remote="321191131145568532" Dst="-1" />
<file name="class.pop3.php" server="ftp.mediaworks.hu//www/wwwtemp/chakra/" local="3443542585" remote="321191131145568532" Dst="-1" />
<file name="class.phpmailer.php" server="ftp.mediaworks.hu//www/wwwtemp/chakra/" local="3443542586" remote="321191131145568532" Dst="-1" />
<file name="class.smtp.php" server="ftp.mediaworks.hu//www/wwwtemp/chakra/" local="3443542588" remote="321191131145568532" Dst="-1" />
<file name="includes.php" server="ftp.mediaworks.hu//www/wwwtemp/chakra/" local="3450268361" remote="323953104366529184" Dst="1" />
<file name="index.html" server="ftp.mediaworks.hu//www/wwwtemp/chakra/" local="3443542606" remote="321191131148725432" Dst="-1" />
<file name="includes.php" server="mediaworks.hu//www/wwwtemp/chakra/" local="130066419600000000" remote="130066419600000000" Dst="1" />
</dwsync>